base_core_utils/__init__.py
base_core_utils/base_repository.py
base_core_utils/base_service.py
base_core_utils/db/__init__.py
base_core_utils/db/session.py
base_core_utils/logger.py
base_core_utils/models/__init__.py
base_core_utils/models/base_model.py
base_core_utils/models/mixins.py
base_core_utils-0.1.0.dist-info/METADATA
base_core_utils-0.1.0.dist-info/WHEEL
base_core_utils-0.1.0.dist-info/RECORD
