Metadata-Version: 2.1
Name: base-core-utils
Version: 0.1.0
Summary: Common base classes for microservices
Author: Dmitry Roshupkin
Author-email: d3po13@yandex.ru
Requires-Python: >=3.11,<4.0
Classifier: Programming Language :: Python :: 3
Classifier: Programming Language :: Python :: 3.11
Requires-Dist: asyncpg (>=0.27.0,<0.28.0)
Requires-Dist: grpcio (>=1.54.0,<2.0.0)
Requires-Dist: grpcio-tools (>=1.54.0,<2.0.0)
Requires-Dist: grpclib (>=0.4.4,<0.5.0)
Requires-Dist: protobuf (>=4.23.0,<5.0.0)
Requires-Dist: sqlalchemy (>=2.0.13,<3.0.0)
